cybersource/__init__.py
cybersource/actions.py
cybersource/admin.py
cybersource/apps.py
cybersource/authentication.py
cybersource/conf.py
cybersource/constants.py
cybersource/cybersoap.py
cybersource/methods.py
cybersource/models.py
cybersource/py.typed
cybersource/signals.py
cybersource/signature.py
cybersource/utils.py
cybersource/views.py
cybersource/fixtures/cybersource-test.yaml
cybersource/locale/es/LC_MESSAGES/django.mo
cybersource/locale/es/LC_MESSAGES/django.po
cybersource/management/__init__.py
cybersource/management/commands/__init__.py
cybersource/management/commands/remove_unreadable_cybersource_profiles.py
cybersource/migrations/0001_initial.py
cybersource/migrations/0002_cybersourcereply_order.py
cybersource/migrations/0003_auto_20160629_1135.py
cybersource/migrations/0004_auto_20180102_1714.py
cybersource/migrations/0005_auto_20180102_1715.py
cybersource/migrations/0006_auto_20190515_1259.py
cybersource/migrations/0007_auto_20190515_1303.py
cybersource/migrations/0008_auto_20190515_1550.py
cybersource/migrations/0009_auto_20190927_0952.py
cybersource/migrations/__init__.py
cybersource/test/__init__.py
cybersource/test/responses.py
cybersource/test/responses/soap-afs-accept.xml
cybersource/test/responses/soap-afs-reject.xml
cybersource/test/responses/soap-afs-review.xml
cybersource/test/responses/soap-auth-accept.xml
cybersource/test/responses/soap-auth-reject.xml
cybersource/test/responses/soap-auth-review.xml
cybersource/test/responses/soap-capture.xml
cybersource/tests/__init__.py
cybersource/tests/factories.py
cybersource/tests/test_checkout.py
cybersource/tests/test_fingerprint.py
cybersource/tests/test_models.py
cybersource/tests/test_review_notification.py
cybersource/tests/test_signer.py
cybersource/tests/test_utils.py
django_oscar_cybersource-9.5.0.dist-info/METADATA
django_oscar_cybersource-9.5.0.dist-info/WHEEL
django_oscar_cybersource-9.5.0.dist-info/licenses/LICENSE
django_oscar_cybersource-9.5.0.dist-info/RECORD
