Metadata-Version: 2.4
Name: django-oscar-cybersource
Version: 9.5.0
Summary: Integration between django-oscar and the Cybersource Secure Acceptance.
Project-URL: Homepage, https://gitlab.com/thelabnyc/django-oscar/django-oscar-cybersource
Project-URL: Repository, https://gitlab.com/thelabnyc/django-oscar/django-oscar-cybersource
Author-email: thelab <thelabdev@thelab.co>
License: ISC
License-File: LICENSE
Requires-Python: >=3.13
Requires-Dist: cryptography<47,>=46.0.3
Requires-Dist: django-oscar-api-checkout<4,>=3.8.1
Requires-Dist: django-oscar-api==3.3.0
Requires-Dist: django-oscar<4.2,>=4.0
Requires-Dist: django-stubs-ext<6,>=5.2.8
Requires-Dist: django>=5.2
Requires-Dist: lxml<7,>=6.0.2
Requires-Dist: phonenumbers<10,>=9.0.20
Requires-Dist: pydantic<3,>=2.12.5
Requires-Dist: python-dateutil<3,>=2.9.0.post0
Requires-Dist: thelabdb>=0.6.0
Requires-Dist: xmlsec<2,>=1.3.17
Requires-Dist: zeep<5,>=4.3.2
